Metadata-Version: 2.1
Name: student-vote
Version: 0.0.2
Summary: This is simple announcement that will show up on the screen.
Home-page: 
Author: Yamini x23166401@student.ncirl.ie
Author-email: x23166401@student.ncirl.ie
License: MIT
Keywords: studentvote
Classifier: Development Status :: 5 - Production/Stable
Classifier: Intended Audience :: Education
Classifier: Operating System :: Microsoft :: Windows :: Windows 10
Classifier: License :: OSI Approved :: MIT License
Classifier: Programming Language :: Python :: 3
License-File: LICENCE.txt
